ChangeLog.md
MANIFEST.in
README.md
setup.py
deblur/__init__.py
deblur/deblurring.py
deblur/parallel_deblur.py
deblur/sequence.py
deblur/workflow.py
deblur.egg-info/PKG-INFO
deblur.egg-info/SOURCES.txt
deblur.egg-info/dependency_links.txt
deblur.egg-info/requires.txt
deblur.egg-info/top_level.txt
deblur/support_files/88_otus.fasta
deblur/support_files/__init__.py
deblur/support_files/artifacts.fa
deblur/test/test_deblurring.py
deblur/test/test_mixedcase.py
deblur/test/test_parallel_deblur.py
deblur/test/test_script.py
deblur/test/test_sequence.py
deblur/test/test_support_files.py
deblur/test/test_workflow.py
deblur/test/data/70_otus.fasta
deblur/test/data/final.s4.biom
deblur/test/data/final.s4.seqs.fa
deblur/test/data/no_trim_results.fasta
deblur/test/data/readme.txt
deblur/test/data/seqs.fq
deblur/test/data/seqs_bad.fq
deblur/test/data/seqs_empty.fasta
deblur/test/data/seqs_illumina1.3.fq
deblur/test/data/seqs_s1.fasta
deblur/test/data/seqs_s2.fasta
deblur/test/data/seqs_s3.fasta
deblur/test/data/seqs_s4.fasta
deblur/test/data/seqs_s5.fasta
deblur/test/data/simset.s1.fasta
deblur/test/data/simset.s2.fasta
deblur/test/data/simset.s3.fasta
deblur/test/data/simset.s4.fasta
deblur/test/data/simset.s5.fasta
deblur/test/data/testmerge.fasta.trim.derep.no_artifacts.msa.deblur.no_chimeras
deblur/test/data/testmerge.fastq.trim.derep.no_artifacts.msa.deblur.no_chimeras
deblur/test/data/testmerge2.fasta.trim.derep.no_artifacts.msa.deblur.no_chimeras
deblur/test/data/usecase_mixedchars/1.SKB7.640196.fastq.trim.derep.no_artifacts.msa.deblur.no_chimeras
deblur/test/data/usecase_mixedchars/1.SKB8.640193.fastq.trim.derep.no_artifacts.deblur.no_chimeras
deblur/test/data/usecase_mixedchars/split/1.SKB7.640196.fastq
deblur/test/data/usecase_mixedchars/split/1.SKB8.640193.fastq
scripts/deblur